metDataModel/__init__.py
metDataModel/core.py
metDataModel/core_simple.py
metDataModel/derived.py
metDataModel/derived_simple.py
metDataModel/simpleTuples.py
metDataModel/util.py
metDataModel/data/__init__.py
tests/__init__.py
metDataModel-0.6.1.dist-info/LICENSE
metDataModel-0.6.1.dist-info/METADATA
metDataModel-0.6.1.dist-info/WHEEL
metDataModel-0.6.1.dist-info/top_level.txt
metDataModel-0.6.1.dist-info/RECORD
