Metadata-Version: 2.1
Name: metDataModel
Version: 0.6.1
Summary: Data models for metabolomics
Home-page: https://github.com/shuzhao-li/metDataModel
Author: Shuzhao Li
Author-email: shuzhao.li@gmail.com
License: BSD license
Keywords: metDataModel
Classifier: Development Status :: 2 - Pre-Alpha
Classifier: Intended Audience :: Developers
Classifier: License :: OSI Approved :: BSD License
Classifier: Natural Language :: English
Classifier: Programming Language :: Python :: 3
Classifier: Programming Language :: Python :: 3.5
Classifier: Programming Language :: Python :: 3.6
Classifier: Programming Language :: Python :: 3.7
Classifier: Programming Language :: Python :: 3.8
Requires-Python: >=3.5
License-File: LICENSE
